phdictionary/__init__.py
phdictionary/dictionary.py
phdictionary/file_manager.py
phdictionary/purifier.py
phdictionary/requestor.py
phdictionary-0.0.4.dist-info/LICENSE
phdictionary-0.0.4.dist-info/METADATA
phdictionary-0.0.4.dist-info/WHEEL
phdictionary-0.0.4.dist-info/top_level.txt
phdictionary-0.0.4.dist-info/RECORD
