Metadata-Version: 2.1
Name: phdictionary
Version: 0.0.4
Summary: PhDictionary. The best tool for language learning
Home-page: https://github.com/RediIVIideR/phdictionary
Author: RediIVIider
Author-email: maksimsserovmail.ru@gmail.com
License: UNKNOWN
Project-URL: Bug Tracker, https://github.com/RediIVIideR/phdictionary
Platform: UNKNOWN
Classifier: Programming Language :: Python :: 3
Classifier: License :: OSI Approved :: MIT License
Classifier: Operating System :: OS Independent
Requires-Python: >=3.6
License-File: LICENSE
